tencentcloud/__init__.py
tencentcloud/intlpartnersmgt/__init__.py
tencentcloud/intlpartnersmgt/v20220928/__init__.py
tencentcloud/intlpartnersmgt/v20220928/errorcodes.py
tencentcloud/intlpartnersmgt/v20220928/intlpartnersmgt_client.py
tencentcloud/intlpartnersmgt/v20220928/models.py
tencentcloud_sdk_python_intlpartnersmgt-3.0.852.dist-info/METADATA
tencentcloud_sdk_python_intlpartnersmgt-3.0.852.dist-info/WHEEL
tencentcloud_sdk_python_intlpartnersmgt-3.0.852.dist-info/top_level.txt
tencentcloud_sdk_python_intlpartnersmgt-3.0.852.dist-info/RECORD
