Metadata-Version: 2.1
Name: tencentcloud-sdk-python-intlpartnersmgt
Version: 3.0.852
Summary: Tencent Cloud Intlpartnersmgt SDK for Python
Home-page: https://github.com/TencentCloud/tencentcloud-sdk-python
Author: Tencent Cloud
Author-email: tencentcloudapi@tencent.com
License: Apache License 2.0
Platform: any
Classifier: Development Status :: 5 - Production/Stable
Classifier: Intended Audience :: Developers
Classifier: License :: OSI Approved :: Apache Software License
Classifier: Programming Language :: Python
Classifier: Programming Language :: Python :: 2.7
Classifier: Programming Language :: Python :: 3
Classifier: Programming Language :: Python :: 3.6
Classifier: Programming Language :: Python :: 3.7
